negargparse/__init__.py
negargparse/negargparse.py
negargparse/py.typed
negargparse-0.2.0.dist-info/LICENSE
negargparse-0.2.0.dist-info/WHEEL
negargparse-0.2.0.dist-info/METADATA
negargparse-0.2.0.dist-info/RECORD
